micromed_io/__init__.py
micromed_io/header.py
micromed_io/in_out.py
micromed_io/scripts/emulate_online_trc.py
micromed_io/scripts/rename_trc.py
micromed_io/scripts/tcp_to_lsl.py
micromed_io/tcp.py
micromed_io/to_mne.py
micromed_io/trc.py
micromed_io-0.4.5.dist-info/entry_points.txt
micromed_io-0.4.5.dist-info/LICENSE
micromed_io-0.4.5.dist-info/METADATA
micromed_io-0.4.5.dist-info/WHEEL
micromed_io-0.4.5.dist-info/RECORD
