Metadata-Version: 2.1
Name: micromed-io
Version: 0.4.5
Summary: A library to read, emulate, and forward Micromed data in standard formats
Author: Etienne de MONTALIVET
Author-email: etienne.demontalivet@protonmail.com
Requires-Python: >=3.9,<4.0
Classifier: Programming Language :: Python :: 3
Classifier: Programming Language :: Python :: 3.9
Classifier: Programming Language :: Python :: 3.10
Classifier: Programming Language :: Python :: 3.11
Classifier: Programming Language :: Python :: 3.12
Requires-Dist: click (>=8.1.7,<9.0.0)
Requires-Dist: mne (>=1.0.0,<2.0.0)
Requires-Dist: pylsl (>=1.16.2,<2.0.0)
